{"type":"Program","start":0,"end":4774,"body":[{"type":"VariableDeclaration","start":0,"end":17,"declarations":[{"type":"VariableDeclarator","start":4,"end":16,"id":{"type":"Identifier","start":4,"end":5,"name":"t"},"init":{"type":"CallExpression","start":8,"end":16,"callee":{"type":"Identifier","start":8,"end":14,"name":"getApp"},"arguments":[],"optional":false}}],"kind":"var"},{"type":"ExpressionStatement","start":19,"end":4774,"expression":{"type":"CallExpression","start":19,"end":4773,"callee":{"type":"Identifier","start":19,"end":23,"name":"Page"},"arguments":[{"type":"ObjectExpression","start":24,"end":4772,"properties":[{"type":"Property","start":30,"end":210,"method":false,"shorthand":false,"computed":false,"key":{"type":"Identifier","start":30,"end":34,"name":"data"},"value":{"type":"ObjectExpression","start":36,"end":210,"properties":[{"type":"Property","start":46,"end":58,"method":false,"shorthand":false,"computed":false,"key":{"type":"Identifier","start":46,"end":54,"name":"rec_name"},"value":{"type":"Literal","start":56,"end":58,"value":"","raw":"\"\""},"kind":"init"},{"type":"Property","start":68,"end":83,"method":false,"shorthand":false,"computed":false,"key":{"type":"Identifier","start":68,"end":79,"name":"cur_address"},"value":{"type":"Literal","start":81,"end":83,"value":"","raw":"\"\""},"kind":"init"},{"type":"Property","start":93,"end":102,"method":false,"shorthand":false,"computed":false,"key":{"type":"Identifier","start":93,"end":98,"name":"phone"},"value":{"type":"Literal","start":100,"end":102,"value":"","raw":"\"\""},"kind":"init"},{"type":"Property","start":112,"end":123,"method":false,"shorthand":false,"computed":false,"key":{"type":"Identifier","start":112,"end":120,"name":"is_first"},"value":{"type":"Literal","start":122,"end":123,"value":0,"raw":"0"},"kind":"init"},{"type":"Property","start":133,"end":148,"method":false,"shorthand":false,"computed":false,"key":{"type":"Identifier","start":133,"end":136,"name":"url"},"value":{"type":"MemberExpression","start":138,"end":148,"object":{"type":"MemberExpression","start":138,"end":144,"object":{"type":"Identifier","start":138,"end":139,"name":"t"},"property":{"type":"Identifier","start":140,"end":144,"name":"page"},"computed":false,"optional":false},"property":{"type":"Identifier","start":145,"end":148,"name":"url"},"computed":false,"optional":false},"kind":"init"},{"type":"Property","start":158,"end":168,"method":false,"shorthand":false,"computed":false,"key":{"type":"Identifier","start":158,"end":164,"name":"userid"},"value":{"type":"Literal","start":166,"end":168,"value":"","raw":"\"\""},"kind":"init"},{"type":"Property","start":178,"end":183,"method":false,"shorthand":false,"computed":false,"key":{"type":"Identifier","start":178,"end":180,"name":"id"},"value":{"type":"Literal","start":182,"end":183,"value":0,"raw":"0"},"kind":"init"},{"type":"Property","start":193,"end":204,"method":false,"shorthand":false,"computed":false,"key":{"type":"Identifier","start":193,"end":200,"name":"address"},"value":{"type":"ArrayExpression","start":202,"end":204,"elements":[]},"kind":"init"}]},"kind":"init"},{"type":"Property","start":216,"end":346,"method":false,"shorthand":false,"computed":false,"key":{"type":"Identifier","start":216,"end":224,"name":"nameText"},"value":{"type":"FunctionExpression","start":226,"end":346,"id":null,"expression":false,"generator":false,"async":false,"params":[{"type":"Identifier","start":235,"end":236,"name":"t"}],"body":{"type":"BlockStatement","start":238,"end":346,"body":[{"type":"ExpressionStatement","start":248,"end":340,"expression":{"type":"SequenceExpression","start":248,"end":339,"expressions":[{"type":"CallExpression","start":248,"end":275,"callee":{"type":"MemberExpression","start":248,"end":259,"object":{"type":"Identifier","start":248,"end":255,"name":"console"},"property":{"type":"Identifier","start":256,"end":259,"name":"log"},"computed":false,"optional":false},"arguments":[{"type":"MemberExpression","start":260,"end":274,"object":{"type":"MemberExpression","start":260,"end":268,"object":{"type":"Identifier","start":260,"end":261,"name":"t"},"property":{"type":"Identifier","start":262,"end":268,"name":"detail"},"computed":false,"optional":false},"property":{"type":"Identifier","start":269,"end":274,"name":"value"},"computed":false,"optional":false}],"optional":false},{"type":"CallExpression","start":277,"end":339,"callee":{"type":"MemberExpression","start":277,"end":289,"object":{"type":"ThisExpression","start":277,"end":281},"property":{"type":"Identifier","start":282,"end":289,"name":"setData"},"computed":false,"optional":false},"arguments":[{"type":"ObjectExpression","start":290,"end":338,"properties":[{"type":"Property","start":304,"end":328,"method":false,"shorthand":false,"computed":false,"key":{"type":"Identifier","start":304,"end":312,"name":"rec_name"},"value":{"type":"MemberExpression","start":314,"end":328,"object":{"type":"MemberExpression","start":314,"end":322,"object":{"type":"Identifier","start":314,"end":315,"name":"t"},"property":{"type":"Identifier","start":316,"end":322,"name":"detail"},"computed":false,"optional":false},"property":{"type":"Identifier","start":323,"end":328,"name":"value"},"computed":false,"optional":false},"kind":"init"}]}],"optional":false}]}}]}},"kind":"init"},{"type":"Property","start":352,"end":478,"method":false,"shorthand":false,"computed":false,"key":{"type":"Identifier","start":352,"end":359,"name":"telText"},"value":{"type":"FunctionExpression","start":361,"end":478,"id":null,"expression":false,"generator":false,"async":false,"params":[{"type":"Identifier","start":370,"end":371,"name":"t"}],"body":{"type":"BlockStatement","start":373,"end":478,"body":[{"type":"ExpressionStatement","start":383,"end":472,"expression":{"type":"SequenceExpression","start":383,"end":471,"expressions":[{"type":"CallExpression","start":383,"end":410,"callee":{"type":"MemberExpression","start":383,"end":394,"object":{"type":"Identifier","start":383,"end":390,"name":"console"},"property":{"type":"Identifier","start":391,"end":394,"name":"log"},"computed":false,"optional":false},"arguments":[{"type":"MemberExpression","start":395,"end":409,"object":{"type":"MemberExpression","start":395,"end":403,"object":{"type":"Identifier","start":395,"end":396,"name":"t"},"property":{"type":"Identifier","start":397,"end":403,"name":"detail"},"computed":false,"optional":false},"property":{"type":"Identifier","start":404,"end":409,"name":"value"},"computed":false,"optional":false}],"optional":false},{"type":"CallExpression","start":412,"end":471,"callee":{"type":"MemberExpression","start":412,"end":424,"object":{"type":"ThisExpression","start":412,"end":416},"property":{"type":"Identifier","start":417,"end":424,"name":"setData"},"computed":false,"optional":false},"arguments":[{"type":"ObjectExpression","start":425,"end":470,"properties":[{"type":"Property","start":439,"end":460,"method":false,"shorthand":false,"computed":false,"key":{"type":"Identifier","start":439,"end":444,"name":"phone"},"value":{"type":"MemberExpression","start":446,"end":460,"object":{"type":"MemberExpression","start":446,"end":454,"object":{"type":"Identifier","start":446,"end":447,"name":"t"},"property":{"type":"Identifier","start":448,"end":454,"name":"detail"},"computed":false,"optional":false},"property":{"type":"Identifier","start":455,"end":460,"name":"value"},"computed":false,"optional":false},"kind":"init"}]}],"optional":false}]}}]}},"kind":"init"},{"type":"Property","start":484,"end":587,"method":false,"shorthand":false,"computed":false,"key":{"type":"Identifier","start":484,"end":491,"name":"addText"},"value":{"type":"FunctionExpression","start":493,"end":587,"id":null,"expression":false,"generator":false,"async":false,"params":[{"type":"Identifier","start":502,"end":503,"name":"t"}],"body":{"type":"BlockStatement","start":505,"end":587,"body":[{"type":"ExpressionStatement","start":515,"end":581,"expression":{"type":"CallExpression","start":515,"end":580,"callee":{"type":"MemberExpression","start":515,"end":527,"object":{"type":"ThisExpression","start":515,"end":519},"property":{"type":"Identifier","start":520,"end":527,"name":"setData"},"computed":false,"optional":false},"arguments":[{"type":"ObjectExpression","start":528,"end":579,"properties":[{"type":"Property","start":542,"end":569,"method":false,"shorthand":false,"computed":false,"key":{"type":"Identifier","start":542,"end":553,"name":"cur_address"},"value":{"type":"MemberExpression","start":555,"end":569,"object":{"type":"MemberExpression","start":555,"end":563,"object":{"type":"Identifier","start":555,"end":556,"name":"t"},"property":{"type":"Identifier","start":557,"end":563,"name":"detail"},"computed":false,"optional":false},"property":{"type":"Identifier","start":564,"end":569,"name":"value"},"computed":false,"optional":false},"kind":"init"}]}],"optional":false}}]}},"kind":"init"},{"type":"Property","start":593,"end":757,"method":false,"shorthand":false,"computed":false,"key":{"type":"Identifier","start":593,"end":606,"name":"switch2Change"},"value":{"type":"FunctionExpression","start":608,"end":757,"id":null,"expression":false,"generator":false,"async":false,"params":[{"type":"Identifier","start":617,"end":618,"name":"t"}],"body":{"type":"BlockStatement","start":620,"end":757,"body":[{"type":"ExpressionStatement","start":630,"end":751,"expression":{"type":"SequenceExpression","start":630,"end":750,"expressions":[{"type":"CallExpression","start":630,"end":686,"callee":{"type":"MemberExpression","start":630,"end":641,"object":{"type":"Identifier","start":630,"end":637,"name":"console"},"property":{"type":"Identifier","start":638,"end":641,"name":"log"},"computed":false,"optional":false},"arguments":[{"type":"Literal","start":642,"end":669,"value":"switch2 发生 change 事件，携带值为","raw":"\"switch2 发生 change 事件，携带值为\""},{"type":"MemberExpression","start":671,"end":685,"object":{"type":"MemberExpression","start":671,"end":679,"object":{"type":"Identifier","start":671,"end":672,"name":"t"},"property":{"type":"Identifier","start":673,"end":679,"name":"detail"},"computed":false,"optional":false},"property":{"type":"Identifier","start":680,"end":685,"name":"value"},"computed":false,"optional":false}],"optional":false},{"type":"CallExpression","start":688,"end":750,"callee":{"type":"MemberExpression","start":688,"end":700,"object":{"type":"ThisExpression","start":688,"end":692},"property":{"type":"Identifier","start":693,"end":700,"name":"setData"},"computed":false,"optional":false},"arguments":[{"type":"ObjectExpression","start":701,"end":749,"properties":[{"type":"Property","start":715,"end":739,"method":false,"shorthand":false,"computed":false,"key":{"type":"Identifier","start":715,"end":723,"name":"is_first"},"value":{"type":"MemberExpression","start":725,"end":739,"object":{"type":"MemberExpression","start":725,"end":733,"object":{"type":"Identifier","start":725,"end":726,"name":"t"},"property":{"type":"Identifier","start":727,"end":733,"name":"detail"},"computed":false,"optional":false},"property":{"type":"Identifier","start":734,"end":739,"name":"value"},"computed":false,"optional":false},"kind":"init"}]}],"optional":false}]}}]}},"kind":"init"},{"type":"Property","start":763,"end":1129,"method":false,"shorthand":false,"computed":false,"key":{"type":"Identifier","start":763,"end":769,"name":"onLoad"},"value":{"type":"FunctionExpression","start":771,"end":1129,"id":null,"expression":false,"generator":false,"async":false,"params":[{"type":"Identifier","start":780,"end":781,"name":"t"}],"body":{"type":"BlockStatement","start":783,"end":1129,"body":[{"type":"VariableDeclaration","start":793,"end":806,"declarations":[{"type":"VariableDeclarator","start":797,"end":805,"id":{"type":"Identifier","start":797,"end":798,"name":"a"},"init":{"type":"ThisExpression","start":801,"end":805}}],"kind":"var"},{"type":"ExpressionStatement","start":815,"end":1123,"expression":{"type":"CallExpression","start":815,"end":1122,"callee":{"type":"MemberExpression","start":815,"end":828,"object":{"type":"Identifier","start":815,"end":817,"name":"wx"},"property":{"type":"Identifier","start":818,"end":828,"name":"getStorage"},"computed":false,"optional":false},"arguments":[{"type":"ObjectExpression","start":829,"end":1121,"properties":[{"type":"Property","start":843,"end":856,"method":false,"shorthand":false,"computed":false,"key":{"type":"Identifier","start":843,"end":846,"name":"key"},"value":{"type":"Literal","start":848,"end":856,"value":"userid","raw":"\"userid\""},"kind":"init"},{"type":"Property","start":870,"end":1111,"method":false,"shorthand":false,"computed":false,"key":{"type":"Identifier","start":870,"end":877,"name":"success"},"value":{"type":"FunctionExpression","start":879,"end":1111,"id":null,"expression":false,"generator":false,"async":false,"params":[{"type":"Identifier","start":888,"end":889,"name":"e"}],"body":{"type":"BlockStatement","start":891,"end":1111,"body":[{"type":"ExpressionStatement","start":909,"end":1097,"expression":{"type":"SequenceExpression","start":909,"end":1096,"expressions":[{"type":"CallExpression","start":909,"end":923,"callee":{"type":"MemberExpression","start":909,"end":920,"object":{"type":"Identifier","start":909,"end":916,"name":"console"},"property":{"type":"Identifier","start":917,"end":920,"name":"log"},"computed":false,"optional":false},"arguments":[{"type":"Identifier","start":921,"end":922,"name":"e"}],"optional":false},{"type":"CallExpression","start":925,"end":990,"callee":{"type":"MemberExpression","start":925,"end":934,"object":{"type":"Identifier","start":925,"end":926,"name":"a"},"property":{"type":"Identifier","start":927,"end":934,"name":"setData"},"computed":false,"optional":false},"arguments":[{"type":"ObjectExpression","start":935,"end":989,"properties":[{"type":"Property","start":957,"end":971,"method":false,"shorthand":false,"computed":false,"key":{"type":"Identifier","start":957,"end":963,"name":"userid"},"value":{"type":"MemberExpression","start":965,"end":971,"object":{"type":"Identifier","start":965,"end":966,"name":"e"},"property":{"type":"Identifier","start":967,"end":971,"name":"data"},"computed":false,"optional":false},"kind":"init"}]}],"optional":false},{"type":"CallExpression","start":992,"end":1009,"callee":{"type":"MemberExpression","start":992,"end":1003,"object":{"type":"Identifier","start":992,"end":999,"name":"console"},"property":{"type":"Identifier","start":1000,"end":1003,"name":"log"},"computed":false,"optional":false},"arguments":[{"type":"MemberExpression","start":1004,"end":1008,"object":{"type":"Identifier","start":1004,"end":1005,"name":"t"},"property":{"type":"Identifier","start":1006,"end":1008,"name":"id"},"computed":false,"optional":false}],"optional":false},{"type":"LogicalExpression","start":1011,"end":1096,"left":{"type":"MemberExpression","start":1011,"end":1015,"object":{"type":"Identifier","start":1011,"end":1012,"name":"t"},"property":{"type":"Identifier","start":1013,"end":1015,"name":"id"},"computed":false,"optional":false},"operator":"&&","right":{"type":"SequenceExpression","start":1020,"end":1095,"expressions":[{"type":"CallExpression","start":1020,"end":1079,"callee":{"type":"MemberExpression","start":1020,"end":1029,"object":{"type":"Identifier","start":1020,"end":1021,"name":"a"},"property":{"type":"Identifier","start":1022,"end":1029,"name":"setData"},"computed":false,"optional":false},"arguments":[{"type":"ObjectExpression","start":1030,"end":1078,"properties":[{"type":"Property","start":1052,"end":1060,"method":false,"shorthand":false,"computed":false,"key":{"type":"Identifier","start":1052,"end":1054,"name":"id"},"value":{"type":"MemberExpression","start":1056,"end":1060,"object":{"type":"Identifier","start":1056,"end":1057,"name":"t"},"property":{"type":"Identifier","start":1058,"end":1060,"name":"id"},"computed":false,"optional":false},"kind":"init"}]}],"optional":false},{"type":"CallExpression","start":1081,"end":1095,"callee":{"type":"MemberExpression","start":1081,"end":1093,"object":{"type":"Identifier","start":1081,"end":1082,"name":"a"},"property":{"type":"Identifier","start":1083,"end":1093,"name":"getAddress"},"computed":false,"optional":false},"arguments":[],"optional":false}]}}]}}]}},"kind":"init"}]}],"optional":false}}]}},"kind":"init"},{"type":"Property","start":1135,"end":1881,"method":false,"shorthand":false,"computed":false,"key":{"type":"Identifier","start":1135,"end":1145,"name":"getAddress"},"value":{"type":"FunctionExpression","start":1147,"end":1881,"id":null,"expression":false,"generator":false,"async":false,"params":[],"body":{"type":"BlockStatement","start":1158,"end":1881,"body":[{"type":"VariableDeclaration","start":1168,"end":1181,"declarations":[{"type":"VariableDeclarator","start":1172,"end":1180,"id":{"type":"Identifier","start":1172,"end":1173,"name":"a"},"init":{"type":"ThisExpression","start":1176,"end":1180}}],"kind":"var"},{"type":"ExpressionStatement","start":1190,"end":1875,"expression":{"type":"SequenceExpression","start":1190,"end":1874,"expressions":[{"type":"CallExpression","start":1190,"end":1212,"callee":{"type":"MemberExpression","start":1190,"end":1201,"object":{"type":"Identifier","start":1190,"end":1197,"name":"console"},"property":{"type":"Identifier","start":1198,"end":1201,"name":"log"},"computed":false,"optional":false},"arguments":[{"type":"MemberExpression","start":1202,"end":1211,"object":{"type":"MemberExpression","start":1202,"end":1208,"object":{"type":"Identifier","start":1202,"end":1203,"name":"a"},"property":{"type":"Identifier","start":1204,"end":1208,"name":"data"},"computed":false,"optional":false},"property":{"type":"Identifier","start":1209,"end":1211,"name":"id"},"computed":false,"optional":false}],"optional":false},{"type":"CallExpression","start":1214,"end":1240,"callee":{"type":"MemberExpression","start":1214,"end":1225,"object":{"type":"Identifier","start":1214,"end":1221,"name":"console"},"property":{"type":"Identifier","start":1222,"end":1225,"name":"log"},"computed":false,"optional":false},"arguments":[{"type":"MemberExpression","start":1226,"end":1239,"object":{"type":"MemberExpression","start":1226,"end":1232,"object":{"type":"Identifier","start":1226,"end":1227,"name":"a"},"property":{"type":"Identifier","start":1228,"end":1232,"name":"data"},"computed":false,"optional":false},"property":{"type":"Identifier","start":1233,"end":1239,"name":"userid"},"computed":false,"optional":false}],"optional":false},{"type":"CallExpression","start":1242,"end":1874,"callee":{"type":"MemberExpression","start":1242,"end":1252,"object":{"type":"Identifier","start":1242,"end":1244,"name":"wx"},"property":{"type":"Identifier","start":1245,"end":1252,"name":"request"},"computed":false,"optional":false},"arguments":[{"type":"ObjectExpression","start":1253,"end":1873,"properties":[{"type":"Property","start":1267,"end":1320,"method":false,"shorthand":false,"computed":false,"key":{"type":"Identifier","start":1267,"end":1270,"name":"url"},"value":{"type":"BinaryExpression","start":1272,"end":1320,"left":{"type":"MemberExpression","start":1272,"end":1282,"object":{"type":"MemberExpression","start":1272,"end":1278,"object":{"type":"Identifier","start":1272,"end":1273,"name":"t"},"property":{"type":"Identifier","start":1274,"end":1278,"name":"page"},"computed":false,"optional":false},"property":{"type":"Identifier","start":1279,"end":1282,"name":"url"},"computed":false,"optional":false},"operator":"+","right":{"type":"Literal","start":1285,"end":1320,"value":"/wx/member.php?act=address_update","raw":"\"/wx/member.php?act=address_update\""}},"kind":"init"},{"type":"Property","start":1334,"end":1348,"method":false,"shorthand":false,"computed":false,"key":{"type":"Identifier","start":1334,"end":1340,"name":"method"},"value":{"type":"Literal","start":1342,"end":1348,"value":"post","raw":"\"post\""},"kind":"init"},{"type":"Property","start":1362,"end":1452,"method":false,"shorthand":false,"computed":false,"key":{"type":"Identifier","start":1362,"end":1366,"name":"data"},"value":{"type":"ObjectExpression","start":1368,"end":1452,"properties":[{"type":"Property","start":1386,"end":1407,"method":false,"shorthand":false,"computed":false,"key":{"type":"Identifier","start":1386,"end":1392,"name":"userid"},"value":{"type":"MemberExpression","start":1394,"end":1407,"object":{"type":"MemberExpression","start":1394,"end":1400,"object":{"type":"Identifier","start":1394,"end":1395,"name":"a"},"property":{"type":"Identifier","start":1396,"end":1400,"name":"data"},"computed":false,"optional":false},"property":{"type":"Identifier","start":1401,"end":1407,"name":"userid"},"computed":false,"optional":false},"kind":"init"},{"type":"Property","start":1425,"end":1438,"method":false,"shorthand":false,"computed":false,"key":{"type":"Identifier","start":1425,"end":1427,"name":"id"},"value":{"type":"MemberExpression","start":1429,"end":1438,"object":{"type":"MemberExpression","start":1429,"end":1435,"object":{"type":"Identifier","start":1429,"end":1430,"name":"a"},"property":{"type":"Identifier","start":1431,"end":1435,"name":"data"},"computed":false,"optional":false},"property":{"type":"Identifier","start":1436,"end":1438,"name":"id"},"computed":false,"optional":false},"kind":"init"}]},"kind":"init"},{"type":"Property","start":1466,"end":1557,"method":false,"shorthand":false,"computed":false,"key":{"type":"Identifier","start":1466,"end":1472,"name":"header"},"value":{"type":"ObjectExpression","start":1474,"end":1557,"properties":[{"type":"Property","start":1492,"end":1543,"method":false,"shorthand":false,"computed":false,"key":{"type":"Literal","start":1492,"end":1506,"value":"content-type","raw":"\"content-type\""},"value":{"type":"Literal","start":1508,"end":1543,"value":"application/x-www-form-urlencoded","raw":"\"application/x-www-form-urlencoded\""},"kind":"init"}]},"kind":"init"},{"type":"Property","start":1571,"end":1863,"method":false,"shorthand":false,"computed":false,"key":{"type":"Identifier","start":1571,"end":1578,"name":"success"},"value":{"type":"FunctionExpression","start":1580,"end":1863,"id":null,"expression":false,"generator":false,"async":false,"params":[{"type":"Identifier","start":1589,"end":1590,"name":"t"}],"body":{"type":"BlockStatement","start":1592,"end":1863,"body":[{"type":"ExpressionStatement","start":1610,"end":1849,"expression":{"type":"SequenceExpression","start":1610,"end":1848,"expressions":[{"type":"CallExpression","start":1610,"end":1629,"callee":{"type":"MemberExpression","start":1610,"end":1621,"object":{"type":"Identifier","start":1610,"end":1617,"name":"console"},"property":{"type":"Identifier","start":1618,"end":1621,"name":"log"},"computed":false,"optional":false},"arguments":[{"type":"MemberExpression","start":1622,"end":1628,"object":{"type":"Identifier","start":1622,"end":1623,"name":"t"},"property":{"type":"Identifier","start":1624,"end":1628,"name":"data"},"computed":false,"optional":false}],"optional":false},{"type":"CallExpression","start":1631,"end":1848,"callee":{"type":"MemberExpression","start":1631,"end":1640,"object":{"type":"Identifier","start":1631,"end":1632,"name":"a"},"property":{"type":"Identifier","start":1633,"end":1640,"name":"setData"},"computed":false,"optional":false},"arguments":[{"type":"ObjectExpression","start":1641,"end":1847,"properties":[{"type":"Property","start":1663,"end":1688,"method":false,"shorthand":false,"computed":false,"key":{"type":"Identifier","start":1663,"end":1671,"name":"rec_name"},"value":{"type":"MemberExpression","start":1673,"end":1688,"object":{"type":"MemberExpression","start":1673,"end":1679,"object":{"type":"Identifier","start":1673,"end":1674,"name":"t"},"property":{"type":"Identifier","start":1675,"end":1679,"name":"data"},"computed":false,"optional":false},"property":{"type":"Identifier","start":1680,"end":1688,"name":"rec_name"},"computed":false,"optional":false},"kind":"init"},{"type":"Property","start":1710,"end":1741,"method":false,"shorthand":false,"computed":false,"key":{"type":"Identifier","start":1710,"end":1721,"name":"cur_address"},"value":{"type":"MemberExpression","start":1723,"end":1741,"object":{"type":"MemberExpression","start":1723,"end":1729,"object":{"type":"Identifier","start":1723,"end":1724,"name":"t"},"property":{"type":"Identifier","start":1725,"end":1729,"name":"data"},"computed":false,"optional":false},"property":{"type":"Identifier","start":1730,"end":1741,"name":"cur_address"},"computed":false,"optional":false},"kind":"init"},{"type":"Property","start":1763,"end":1782,"method":false,"shorthand":false,"computed":false,"key":{"type":"Identifier","start":1763,"end":1768,"name":"phone"},"value":{"type":"MemberExpression","start":1770,"end":1782,"object":{"type":"MemberExpression","start":1770,"end":1776,"object":{"type":"Identifier","start":1770,"end":1771,"name":"t"},"property":{"type":"Identifier","start":1772,"end":1776,"name":"data"},"computed":false,"optional":false},"property":{"type":"Identifier","start":1777,"end":1782,"name":"phone"},"computed":false,"optional":false},"kind":"init"},{"type":"Property","start":1804,"end":1829,"method":false,"shorthand":false,"computed":false,"key":{"type":"Identifier","start":1804,"end":1812,"name":"is_first"},"value":{"type":"MemberExpression","start":1814,"end":1829,"object":{"type":"MemberExpression","start":1814,"end":1820,"object":{"type":"Identifier","start":1814,"end":1815,"name":"t"},"property":{"type":"Identifier","start":1816,"end":1820,"name":"data"},"computed":false,"optional":false},"property":{"type":"Identifier","start":1821,"end":1829,"name":"is_first"},"computed":false,"optional":false},"kind":"init"}]}],"optional":false}]}}]}},"kind":"init"}]}],"optional":false}]}}]}},"kind":"init"},{"type":"Property","start":1887,"end":2766,"method":false,"shorthand":false,"computed":false,"key":{"type":"Identifier","start":1887,"end":1893,"name":"submit"},"value":{"type":"FunctionExpression","start":1895,"end":2766,"id":null,"expression":false,"generator":false,"async":false,"params":[],"body":{"type":"BlockStatement","start":1906,"end":2766,"body":[{"type":"VariableDeclaration","start":1916,"end":1991,"declarations":[{"type":"VariableDeclarator","start":1920,"end":1942,"id":{"type":"Identifier","start":1920,"end":1921,"name":"t"},"init":{"type":"MemberExpression","start":1924,"end":1942,"object":{"type":"MemberExpression","start":1924,"end":1933,"object":{"type":"ThisExpression","start":1924,"end":1928},"property":{"type":"Identifier","start":1929,"end":1933,"name":"data"},"computed":false,"optional":false},"property":{"type":"Identifier","start":1934,"end":1942,"name":"rec_name"},"computed":false,"optional":false}},{"type":"VariableDeclarator","start":1944,"end":1969,"id":{"type":"Identifier","start":1944,"end":1945,"name":"a"},"init":{"type":"MemberExpression","start":1948,"end":1969,"object":{"type":"MemberExpression","start":1948,"end":1957,"object":{"type":"ThisExpression","start":1948,"end":1952},"property":{"type":"Identifier","start":1953,"end":1957,"name":"data"},"computed":false,"optional":false},"property":{"type":"Identifier","start":1958,"end":1969,"name":"cur_address"},"computed":false,"optional":false}},{"type":"VariableDeclarator","start":1971,"end":1990,"id":{"type":"Identifier","start":1971,"end":1972,"name":"e"},"init":{"type":"MemberExpression","start":1975,"end":1990,"object":{"type":"MemberExpression","start":1975,"end":1984,"object":{"type":"ThisExpression","start":1975,"end":1979},"property":{"type":"Identifier","start":1980,"end":1984,"name":"data"},"computed":false,"optional":false},"property":{"type":"Identifier","start":1985,"end":1990,"name":"phone"},"computed":false,"optional":false}}],"kind":"var"},{"type":"ReturnStatement","start":2000,"end":2760,"argument":{"type":"SequenceExpression","start":2007,"end":2759,"expressions":[{"type":"ConditionalExpression","start":2007,"end":2134,"test":{"type":"BinaryExpression","start":2007,"end":2030,"left":{"type":"Literal","start":2007,"end":2008,"value":1,"raw":"1"},"operator":"==","right":{"type":"MemberExpression","start":2012,"end":2030,"object":{"type":"MemberExpression","start":2012,"end":2021,"object":{"type":"ThisExpression","start":2012,"end":2016},"property":{"type":"Identifier","start":2017,"end":2021,"name":"data"},"computed":false,"optional":false},"property":{"type":"Identifier","start":2022,"end":2030,"name":"is_first"},"computed":false,"optional":false}},"consequent":{"type":"CallExpression","start":2033,"end":2082,"callee":{"type":"MemberExpression","start":2033,"end":2045,"object":{"type":"ThisExpression","start":2033,"end":2037},"property":{"type":"Identifier","start":2038,"end":2045,"name":"setData"},"computed":false,"optional":false},"arguments":[{"type":"ObjectExpression","start":2046,"end":2081,"properties":[{"type":"Property","start":2060,"end":2071,"method":false,"shorthand":false,"computed":false,"key":{"type":"Identifier","start":2060,"end":2068,"name":"is_first"},"value":{"type":"Literal","start":2070,"end":2071,"value":1,"raw":"1"},"kind":"init"}]}],"optional":false},"alternate":{"type":"CallExpression","start":2085,"end":2134,"callee":{"type":"MemberExpression","start":2085,"end":2097,"object":{"type":"ThisExpression","start":2085,"end":2089},"property":{"type":"Identifier","start":2090,"end":2097,"name":"setData"},"computed":false,"optional":false},"arguments":[{"type":"ObjectExpression","start":2098,"end":2133,"properties":[{"type":"Property","start":2112,"end":2123,"method":false,"shorthand":false,"computed":false,"key":{"type":"Identifier","start":2112,"end":2120,"name":"is_first"},"value":{"type":"Literal","start":2122,"end":2123,"value":0,"raw":"0"},"kind":"init"}]}],"optional":false}},{"type":"ConditionalExpression","start":2136,"end":2759,"test":{"type":"BinaryExpression","start":2136,"end":2143,"left":{"type":"Literal","start":2136,"end":2138,"value":"","raw":"\"\""},"operator":"==","right":{"type":"Identifier","start":2142,"end":2143,"name":"t"}},"consequent":{"type":"SequenceExpression","start":2147,"end":2263,"expressions":[{"type":"CallExpression","start":2147,"end":2259,"callee":{"type":"MemberExpression","start":2147,"end":2159,"object":{"type":"Identifier","start":2147,"end":2149,"name":"wx"},"property":{"type":"Identifier","start":2150,"end":2159,"name":"showToast"},"computed":false,"optional":false},"arguments":[{"type":"ObjectExpression","start":2160,"end":2258,"properties":[{"type":"Property","start":2174,"end":2192,"method":false,"shorthand":false,"computed":false,"key":{"type":"Identifier","start":2174,"end":2179,"name":"title"},"value":{"type":"Literal","start":2181,"end":2192,"value":"请输入收货人姓名！","raw":"\"请输入收货人姓名！\""},"kind":"init"},{"type":"Property","start":2206,"end":2221,"method":false,"shorthand":false,"computed":false,"key":{"type":"Identifier","start":2206,"end":2210,"name":"icon"},"value":{"type":"Literal","start":2212,"end":2221,"value":"loading","raw":"\"loading\""},"kind":"init"},{"type":"Property","start":2235,"end":2248,"method":false,"shorthand":false,"computed":false,"key":{"type":"Identifier","start":2235,"end":2243,"name":"duration"},"value":{"type":"Literal","start":2245,"end":2248,"value":1000,"raw":"1e3"},"kind":"init"}]}],"optional":false},{"type":"UnaryExpression","start":2261,"end":2263,"operator":"!","prefix":true,"argument":{"type":"Literal","start":2262,"end":2263,"value":1,"raw":"1"}}]},"alternate":{"type":"ConditionalExpression","start":2267,"end":2759,"test":{"type":"BinaryExpression","start":2267,"end":2274,"left":{"type":"Literal","start":2267,"end":2269,"value":"","raw":"\"\""},"operator":"==","right":{"type":"Identifier","start":2273,"end":2274,"name":"e"}},"consequent":{"type":"SequenceExpression","start":2278,"end":2391,"expressions":[{"type":"CallExpression","start":2278,"end":2387,"callee":{"type":"MemberExpression","start":2278,"end":2290,"object":{"type":"Identifier","start":2278,"end":2280,"name":"wx"},"property":{"type":"Identifier","start":2281,"end":2290,"name":"showToast"},"computed":false,"optional":false},"arguments":[{"type":"ObjectExpression","start":2291,"end":2386,"properties":[{"type":"Property","start":2305,"end":2320,"method":false,"shorthand":false,"computed":false,"key":{"type":"Identifier","start":2305,"end":2310,"name":"title"},"value":{"type":"Literal","start":2312,"end":2320,"value":"请输入手机号","raw":"\"请输入手机号\""},"kind":"init"},{"type":"Property","start":2334,"end":2349,"method":false,"shorthand":false,"computed":false,"key":{"type":"Identifier","start":2334,"end":2338,"name":"icon"},"value":{"type":"Literal","start":2340,"end":2349,"value":"loading","raw":"\"loading\""},"kind":"init"},{"type":"Property","start":2363,"end":2376,"method":false,"shorthand":false,"computed":false,"key":{"type":"Identifier","start":2363,"end":2371,"name":"duration"},"value":{"type":"Literal","start":2373,"end":2376,"value":1000,"raw":"1e3"},"kind":"init"}]}],"optional":false},{"type":"UnaryExpression","start":2389,"end":2391,"operator":"!","prefix":true,"argument":{"type":"Literal","start":2390,"end":2391,"value":1,"raw":"1"}}]},"alternate":{"type":"ConditionalExpression","start":2395,"end":2759,"test":{"type":"CallExpression","start":2395,"end":2429,"callee":{"type":"MemberExpression","start":2395,"end":2426,"object":{"type":"Literal","start":2395,"end":2421,"value":{},"raw":"/^[1][3,4,5,7,8][0-9]{9}$/","regex":{"pattern":"^[1][3,4,5,7,8][0-9]{9}$","flags":""}},"property":{"type":"Identifier","start":2422,"end":2426,"name":"test"},"computed":false,"optional":false},"arguments":[{"type":"Identifier","start":2427,"end":2428,"name":"e"}],"optional":false},"consequent":{"type":"ConditionalExpression","start":2432,"end":2640,"test":{"type":"LogicalExpression","start":2432,"end":2455,"left":{"type":"BinaryExpression","start":2432,"end":2439,"left":{"type":"Literal","start":2432,"end":2434,"value":"","raw":"\"\""},"operator":"==","right":{"type":"Identifier","start":2438,"end":2439,"name":"a"}},"operator":"&&","right":{"type":"BinaryExpression","start":2443,"end":2455,"left":{"type":"MemberExpression","start":2443,"end":2451,"object":{"type":"Identifier","start":2443,"end":2444,"name":"a"},"property":{"type":"Identifier","start":2445,"end":2451,"name":"length"},"computed":false,"optional":false},"operator":"<","right":{"type":"Literal","start":2454,"end":2455,"value":5,"raw":"5"}}},"consequent":{"type":"SequenceExpression","start":2459,"end":2574,"expressions":[{"type":"CallExpression","start":2459,"end":2570,"callee":{"type":"MemberExpression","start":2459,"end":2471,"object":{"type":"Identifier","start":2459,"end":2461,"name":"wx"},"property":{"type":"Identifier","start":2462,"end":2471,"name":"showToast"},"computed":false,"optional":false},"arguments":[{"type":"ObjectExpression","start":2472,"end":2569,"properties":[{"type":"Property","start":2486,"end":2503,"method":false,"shorthand":false,"computed":false,"key":{"type":"Identifier","start":2486,"end":2491,"name":"title"},"value":{"type":"Literal","start":2493,"end":2503,"value":"请输入详细地址！","raw":"\"请输入详细地址！\""},"kind":"init"},{"type":"Property","start":2517,"end":2532,"method":false,"shorthand":false,"computed":false,"key":{"type":"Identifier","start":2517,"end":2521,"name":"icon"},"value":{"type":"Literal","start":2523,"end":2532,"value":"loading","raw":"\"loading\""},"kind":"init"},{"type":"Property","start":2546,"end":2559,"method":false,"shorthand":false,"computed":false,"key":{"type":"Identifier","start":2546,"end":2554,"name":"duration"},"value":{"type":"Literal","start":2556,"end":2559,"value":1000,"raw":"1e3"},"kind":"init"}]}],"optional":false},{"type":"UnaryExpression","start":2572,"end":2574,"operator":"!","prefix":true,"argument":{"type":"Literal","start":2573,"end":2574,"value":1,"raw":"1"}}]},"alternate":{"type":"UnaryExpression","start":2578,"end":2640,"operator":"void","prefix":true,"argument":{"type":"ConditionalExpression","start":2584,"end":2639,"test":{"type":"MemberExpression","start":2584,"end":2596,"object":{"type":"MemberExpression","start":2584,"end":2593,"object":{"type":"ThisExpression","start":2584,"end":2588},"property":{"type":"Identifier","start":2589,"end":2593,"name":"data"},"computed":false,"optional":false},"property":{"type":"Identifier","start":2594,"end":2596,"name":"id"},"computed":false,"optional":false},"consequent":{"type":"CallExpression","start":2599,"end":2619,"callee":{"type":"MemberExpression","start":2599,"end":2617,"object":{"type":"ThisExpression","start":2599,"end":2603},"property":{"type":"Identifier","start":2604,"end":2617,"name":"updateAddress"},"computed":false,"optional":false},"arguments":[],"optional":false},"alternate":{"type":"CallExpression","start":2622,"end":2639,"callee":{"type":"MemberExpression","start":2622,"end":2637,"object":{"type":"ThisExpression","start":2622,"end":2626},"property":{"type":"Identifier","start":2627,"end":2637,"name":"addAddress"},"computed":false,"optional":false},"arguments":[],"optional":false}}}},"alternate":{"type":"SequenceExpression","start":2644,"end":2758,"expressions":[{"type":"CallExpression","start":2644,"end":2754,"callee":{"type":"MemberExpression","start":2644,"end":2656,"object":{"type":"Identifier","start":2644,"end":2646,"name":"wx"},"property":{"type":"Identifier","start":2647,"end":2656,"name":"showToast"},"computed":false,"optional":false},"arguments":[{"type":"ObjectExpression","start":2657,"end":2753,"properties":[{"type":"Property","start":2671,"end":2687,"method":false,"shorthand":false,"computed":false,"key":{"type":"Identifier","start":2671,"end":2676,"name":"title"},"value":{"type":"Literal","start":2678,"end":2687,"value":"手机号输入错误","raw":"\"手机号输入错误\""},"kind":"init"},{"type":"Property","start":2701,"end":2716,"method":false,"shorthand":false,"computed":false,"key":{"type":"Identifier","start":2701,"end":2705,"name":"icon"},"value":{"type":"Literal","start":2707,"end":2716,"value":"loading","raw":"\"loading\""},"kind":"init"},{"type":"Property","start":2730,"end":2743,"method":false,"shorthand":false,"computed":false,"key":{"type":"Identifier","start":2730,"end":2738,"name":"duration"},"value":{"type":"Literal","start":2740,"end":2743,"value":1000,"raw":"1e3"},"kind":"init"}]}],"optional":false},{"type":"UnaryExpression","start":2756,"end":2758,"operator":"!","prefix":true,"argument":{"type":"Literal","start":2757,"end":2758,"value":1,"raw":"1"}}]}}}}]}}]}},"kind":"init"},{"type":"Property","start":2772,"end":3593,"method":false,"shorthand":false,"computed":false,"key":{"type":"Identifier","start":2772,"end":2782,"name":"addAddress"},"value":{"type":"FunctionExpression","start":2784,"end":3593,"id":null,"expression":false,"generator":false,"async":false,"params":[],"body":{"type":"BlockStatement","start":2795,"end":3593,"body":[{"type":"ExpressionStatement","start":2805,"end":3587,"expression":{"type":"SequenceExpression","start":2805,"end":3586,"expressions":[{"type":"CallExpression","start":2805,"end":2834,"callee":{"type":"MemberExpression","start":2805,"end":2816,"object":{"type":"Identifier","start":2805,"end":2812,"name":"console"},"property":{"type":"Identifier","start":2813,"end":2816,"name":"log"},"computed":false,"optional":false},"arguments":[{"type":"MemberExpression","start":2817,"end":2833,"object":{"type":"MemberExpression","start":2817,"end":2826,"object":{"type":"ThisExpression","start":2817,"end":2821},"property":{"type":"Identifier","start":2822,"end":2826,"name":"data"},"computed":false,"optional":false},"property":{"type":"Identifier","start":2827,"end":2833,"name":"userid"},"computed":false,"optional":false}],"optional":false},{"type":"CallExpression","start":2836,"end":3586,"callee":{"type":"MemberExpression","start":2836,"end":2846,"object":{"type":"Identifier","start":2836,"end":2838,"name":"wx"},"property":{"type":"Identifier","start":2839,"end":2846,"name":"request"},"computed":false,"optional":false},"arguments":[{"type":"ObjectExpression","start":2847,"end":3585,"properties":[{"type":"Property","start":2861,"end":2911,"method":false,"shorthand":false,"computed":false,"key":{"type":"Identifier","start":2861,"end":2864,"name":"url"},"value":{"type":"BinaryExpression","start":2866,"end":2911,"left":{"type":"MemberExpression","start":2866,"end":2876,"object":{"type":"MemberExpression","start":2866,"end":2872,"object":{"type":"Identifier","start":2866,"end":2867,"name":"t"},"property":{"type":"Identifier","start":2868,"end":2872,"name":"page"},"computed":false,"optional":false},"property":{"type":"Identifier","start":2873,"end":2876,"name":"url"},"computed":false,"optional":false},"operator":"+","right":{"type":"Literal","start":2879,"end":2911,"value":"/wx/member.php?act=address_jud","raw":"\"/wx/member.php?act=address_jud\""}},"kind":"init"},{"type":"Property","start":2925,"end":2939,"method":false,"shorthand":false,"computed":false,"key":{"type":"Identifier","start":2925,"end":2931,"name":"method"},"value":{"type":"Literal","start":2933,"end":2939,"value":"post","raw":"\"post\""},"kind":"init"},{"type":"Property","start":2953,"end":3199,"method":false,"shorthand":false,"computed":false,"key":{"type":"Identifier","start":2953,"end":2957,"name":"data"},"value":{"type":"ObjectExpression","start":2959,"end":3199,"properties":[{"type":"Property","start":2977,"end":3001,"method":false,"shorthand":false,"computed":false,"key":{"type":"Identifier","start":2977,"end":2983,"name":"userid"},"value":{"type":"MemberExpression","start":2985,"end":3001,"object":{"type":"MemberExpression","start":2985,"end":2994,"object":{"type":"ThisExpression","start":2985,"end":2989},"property":{"type":"Identifier","start":2990,"end":2994,"name":"data"},"computed":false,"optional":false},"property":{"type":"Identifier","start":2995,"end":3001,"name":"userid"},"computed":false,"optional":false},"kind":"init"},{"type":"Property","start":3019,"end":3047,"method":false,"shorthand":false,"computed":false,"key":{"type":"Identifier","start":3019,"end":3027,"name":"is_first"},"value":{"type":"MemberExpression","start":3029,"end":3047,"object":{"type":"MemberExpression","start":3029,"end":3038,"object":{"type":"ThisExpression","start":3029,"end":3033},"property":{"type":"Identifier","start":3034,"end":3038,"name":"data"},"computed":false,"optional":false},"property":{"type":"Identifier","start":3039,"end":3047,"name":"is_first"},"computed":false,"optional":false},"kind":"init"},{"type":"Property","start":3065,"end":3093,"method":false,"shorthand":false,"computed":false,"key":{"type":"Identifier","start":3065,"end":3073,"name":"rec_name"},"value":{"type":"MemberExpression","start":3075,"end":3093,"object":{"type":"MemberExpression","start":3075,"end":3084,"object":{"type":"ThisExpression","start":3075,"end":3079},"property":{"type":"Identifier","start":3080,"end":3084,"name":"data"},"computed":false,"optional":false},"property":{"type":"Identifier","start":3085,"end":3093,"name":"rec_name"},"computed":false,"optional":false},"kind":"init"},{"type":"Property","start":3111,"end":3133,"method":false,"shorthand":false,"computed":false,"key":{"type":"Identifier","start":3111,"end":3116,"name":"phone"},"value":{"type":"MemberExpression","start":3118,"end":3133,"object":{"type":"MemberExpression","start":3118,"end":3127,"object":{"type":"ThisExpression","start":3118,"end":3122},"property":{"type":"Identifier","start":3123,"end":3127,"name":"data"},"computed":false,"optional":false},"property":{"type":"Identifier","start":3128,"end":3133,"name":"phone"},"computed":false,"optional":false},"kind":"init"},{"type":"Property","start":3151,"end":3185,"method":false,"shorthand":false,"computed":false,"key":{"type":"Identifier","start":3151,"end":3162,"name":"cur_address"},"value":{"type":"MemberExpression","start":3164,"end":3185,"object":{"type":"MemberExpression","start":3164,"end":3173,"object":{"type":"ThisExpression","start":3164,"end":3168},"property":{"type":"Identifier","start":3169,"end":3173,"name":"data"},"computed":false,"optional":false},"property":{"type":"Identifier","start":3174,"end":3185,"name":"cur_address"},"computed":false,"optional":false},"kind":"init"}]},"kind":"init"},{"type":"Property","start":3213,"end":3304,"method":false,"shorthand":false,"computed":false,"key":{"type":"Identifier","start":3213,"end":3219,"name":"header"},"value":{"type":"ObjectExpression","start":3221,"end":3304,"properties":[{"type":"Property","start":3239,"end":3290,"method":false,"shorthand":false,"computed":false,"key":{"type":"Literal","start":3239,"end":3253,"value":"content-type","raw":"\"content-type\""},"value":{"type":"Literal","start":3255,"end":3290,"value":"application/x-www-form-urlencoded","raw":"\"application/x-www-form-urlencoded\""},"kind":"init"}]},"kind":"init"},{"type":"Property","start":3318,"end":3575,"method":false,"shorthand":false,"computed":false,"key":{"type":"Identifier","start":3318,"end":3325,"name":"success"},"value":{"type":"FunctionExpression","start":3327,"end":3575,"id":null,"expression":false,"generator":false,"async":false,"params":[{"type":"Identifier","start":3336,"end":3337,"name":"t"}],"body":{"type":"BlockStatement","start":3339,"end":3575,"body":[{"type":"ExpressionStatement","start":3357,"end":3561,"expression":{"type":"SequenceExpression","start":3357,"end":3560,"expressions":[{"type":"CallExpression","start":3357,"end":3376,"callee":{"type":"MemberExpression","start":3357,"end":3368,"object":{"type":"Identifier","start":3357,"end":3364,"name":"console"},"property":{"type":"Identifier","start":3365,"end":3368,"name":"log"},"computed":false,"optional":false},"arguments":[{"type":"MemberExpression","start":3369,"end":3375,"object":{"type":"Identifier","start":3369,"end":3370,"name":"t"},"property":{"type":"Identifier","start":3371,"end":3375,"name":"data"},"computed":false,"optional":false}],"optional":false},{"type":"ConditionalExpression","start":3378,"end":3560,"test":{"type":"BinaryExpression","start":3378,"end":3394,"left":{"type":"Literal","start":3378,"end":3379,"value":0,"raw":"0"},"operator":"==","right":{"type":"MemberExpression","start":3383,"end":3394,"object":{"type":"MemberExpression","start":3383,"end":3389,"object":{"type":"Identifier","start":3383,"end":3384,"name":"t"},"property":{"type":"Identifier","start":3385,"end":3389,"name":"data"},"computed":false,"optional":false},"property":{"type":"Identifier","start":3390,"end":3394,"name":"code"},"computed":false,"optional":false}},"consequent":{"type":"CallExpression","start":3397,"end":3414,"callee":{"type":"MemberExpression","start":3397,"end":3412,"object":{"type":"Identifier","start":3397,"end":3399,"name":"wx"},"property":{"type":"Identifier","start":3400,"end":3412,"name":"navigateBack"},"computed":false,"optional":false},"arguments":[],"optional":false},"alternate":{"type":"CallExpression","start":3417,"end":3560,"callee":{"type":"MemberExpression","start":3417,"end":3429,"object":{"type":"Identifier","start":3417,"end":3419,"name":"wx"},"property":{"type":"Identifier","start":3420,"end":3429,"name":"showToast"},"computed":false,"optional":false},"arguments":[{"type":"ObjectExpression","start":3430,"end":3559,"properties":[{"type":"Property","start":3452,"end":3469,"method":false,"shorthand":false,"computed":false,"key":{"type":"Identifier","start":3452,"end":3457,"name":"title"},"value":{"type":"MemberExpression","start":3459,"end":3469,"object":{"type":"MemberExpression","start":3459,"end":3465,"object":{"type":"Identifier","start":3459,"end":3460,"name":"t"},"property":{"type":"Identifier","start":3461,"end":3465,"name":"data"},"computed":false,"optional":false},"property":{"type":"Identifier","start":3466,"end":3469,"name":"msg"},"computed":false,"optional":false},"kind":"init"},{"type":"Property","start":3491,"end":3506,"method":false,"shorthand":false,"computed":false,"key":{"type":"Identifier","start":3491,"end":3495,"name":"icon"},"value":{"type":"Literal","start":3497,"end":3506,"value":"loading","raw":"\"loading\""},"kind":"init"},{"type":"Property","start":3528,"end":3541,"method":false,"shorthand":false,"computed":false,"key":{"type":"Identifier","start":3528,"end":3536,"name":"duration"},"value":{"type":"Literal","start":3538,"end":3541,"value":10000,"raw":"1e4"},"kind":"init"}]}],"optional":false}}]}}]}},"kind":"init"}]}],"optional":false}]}}]}},"kind":"init"},{"type":"Property","start":3599,"end":4459,"method":false,"shorthand":false,"computed":false,"key":{"type":"Identifier","start":3599,"end":3612,"name":"updateAddress"},"value":{"type":"FunctionExpression","start":3614,"end":4459,"id":null,"expression":false,"generator":false,"async":false,"params":[],"body":{"type":"BlockStatement","start":3625,"end":4459,"body":[{"type":"ExpressionStatement","start":3635,"end":4453,"expression":{"type":"SequenceExpression","start":3635,"end":4452,"expressions":[{"type":"CallExpression","start":3635,"end":3666,"callee":{"type":"MemberExpression","start":3635,"end":3646,"object":{"type":"Identifier","start":3635,"end":3642,"name":"console"},"property":{"type":"Identifier","start":3643,"end":3646,"name":"log"},"computed":false,"optional":false},"arguments":[{"type":"MemberExpression","start":3647,"end":3665,"object":{"type":"MemberExpression","start":3647,"end":3656,"object":{"type":"ThisExpression","start":3647,"end":3651},"property":{"type":"Identifier","start":3652,"end":3656,"name":"data"},"computed":false,"optional":false},"property":{"type":"Identifier","start":3657,"end":3665,"name":"is_first"},"computed":false,"optional":false}],"optional":false},{"type":"CallExpression","start":3668,"end":4452,"callee":{"type":"MemberExpression","start":3668,"end":3678,"object":{"type":"Identifier","start":3668,"end":3670,"name":"wx"},"property":{"type":"Identifier","start":3671,"end":3678,"name":"request"},"computed":false,"optional":false},"arguments":[{"type":"ObjectExpression","start":3679,"end":4451,"properties":[{"type":"Property","start":3693,"end":3743,"method":false,"shorthand":false,"computed":false,"key":{"type":"Identifier","start":3693,"end":3696,"name":"url"},"value":{"type":"BinaryExpression","start":3698,"end":3743,"left":{"type":"MemberExpression","start":3698,"end":3708,"object":{"type":"MemberExpression","start":3698,"end":3704,"object":{"type":"Identifier","start":3698,"end":3699,"name":"t"},"property":{"type":"Identifier","start":3700,"end":3704,"name":"page"},"computed":false,"optional":false},"property":{"type":"Identifier","start":3705,"end":3708,"name":"url"},"computed":false,"optional":false},"operator":"+","right":{"type":"Literal","start":3711,"end":3743,"value":"/wx/member.php?act=addr_update","raw":"\"/wx/member.php?act=addr_update\""}},"kind":"init"},{"type":"Property","start":3757,"end":3771,"method":false,"shorthand":false,"computed":false,"key":{"type":"Identifier","start":3757,"end":3763,"name":"method"},"value":{"type":"Literal","start":3765,"end":3771,"value":"post","raw":"\"post\""},"kind":"init"},{"type":"Property","start":3785,"end":4065,"method":false,"shorthand":false,"computed":false,"key":{"type":"Identifier","start":3785,"end":3789,"name":"data"},"value":{"type":"ObjectExpression","start":3791,"end":4065,"properties":[{"type":"Property","start":3809,"end":3825,"method":false,"shorthand":false,"computed":false,"key":{"type":"Identifier","start":3809,"end":3811,"name":"id"},"value":{"type":"MemberExpression","start":3813,"end":3825,"object":{"type":"MemberExpression","start":3813,"end":3822,"object":{"type":"ThisExpression","start":3813,"end":3817},"property":{"type":"Identifier","start":3818,"end":3822,"name":"data"},"computed":false,"optional":false},"property":{"type":"Identifier","start":3823,"end":3825,"name":"id"},"computed":false,"optional":false},"kind":"init"},{"type":"Property","start":3843,"end":3867,"method":false,"shorthand":false,"computed":false,"key":{"type":"Identifier","start":3843,"end":3849,"name":"userid"},"value":{"type":"MemberExpression","start":3851,"end":3867,"object":{"type":"MemberExpression","start":3851,"end":3860,"object":{"type":"ThisExpression","start":3851,"end":3855},"property":{"type":"Identifier","start":3856,"end":3860,"name":"data"},"computed":false,"optional":false},"property":{"type":"Identifier","start":3861,"end":3867,"name":"userid"},"computed":false,"optional":false},"kind":"init"},{"type":"Property","start":3885,"end":3913,"method":false,"shorthand":false,"computed":false,"key":{"type":"Identifier","start":3885,"end":3893,"name":"is_first"},"value":{"type":"MemberExpression","start":3895,"end":3913,"object":{"type":"MemberExpression","start":3895,"end":3904,"object":{"type":"ThisExpression","start":3895,"end":3899},"property":{"type":"Identifier","start":3900,"end":3904,"name":"data"},"computed":false,"optional":false},"property":{"type":"Identifier","start":3905,"end":3913,"name":"is_first"},"computed":false,"optional":false},"kind":"init"},{"type":"Property","start":3931,"end":3959,"method":false,"shorthand":false,"computed":false,"key":{"type":"Identifier","start":3931,"end":3939,"name":"rec_name"},"value":{"type":"MemberExpression","start":3941,"end":3959,"object":{"type":"MemberExpression","start":3941,"end":3950,"object":{"type":"ThisExpression","start":3941,"end":3945},"property":{"type":"Identifier","start":3946,"end":3950,"name":"data"},"computed":false,"optional":false},"property":{"type":"Identifier","start":3951,"end":3959,"name":"rec_name"},"computed":false,"optional":false},"kind":"init"},{"type":"Property","start":3977,"end":3999,"method":false,"shorthand":false,"computed":false,"key":{"type":"Identifier","start":3977,"end":3982,"name":"phone"},"value":{"type":"MemberExpression","start":3984,"end":3999,"object":{"type":"MemberExpression","start":3984,"end":3993,"object":{"type":"ThisExpression","start":3984,"end":3988},"property":{"type":"Identifier","start":3989,"end":3993,"name":"data"},"computed":false,"optional":false},"property":{"type":"Identifier","start":3994,"end":3999,"name":"phone"},"computed":false,"optional":false},"kind":"init"},{"type":"Property","start":4017,"end":4051,"method":false,"shorthand":false,"computed":false,"key":{"type":"Identifier","start":4017,"end":4028,"name":"cur_address"},"value":{"type":"MemberExpression","start":4030,"end":4051,"object":{"type":"MemberExpression","start":4030,"end":4039,"object":{"type":"ThisExpression","start":4030,"end":4034},"property":{"type":"Identifier","start":4035,"end":4039,"name":"data"},"computed":false,"optional":false},"property":{"type":"Identifier","start":4040,"end":4051,"name":"cur_address"},"computed":false,"optional":false},"kind":"init"}]},"kind":"init"},{"type":"Property","start":4079,"end":4170,"method":false,"shorthand":false,"computed":false,"key":{"type":"Identifier","start":4079,"end":4085,"name":"header"},"value":{"type":"ObjectExpression","start":4087,"end":4170,"properties":[{"type":"Property","start":4105,"end":4156,"method":false,"shorthand":false,"computed":false,"key":{"type":"Literal","start":4105,"end":4119,"value":"content-type","raw":"\"content-type\""},"value":{"type":"Literal","start":4121,"end":4156,"value":"application/x-www-form-urlencoded","raw":"\"application/x-www-form-urlencoded\""},"kind":"init"}]},"kind":"init"},{"type":"Property","start":4184,"end":4441,"method":false,"shorthand":false,"computed":false,"key":{"type":"Identifier","start":4184,"end":4191,"name":"success"},"value":{"type":"FunctionExpression","start":4193,"end":4441,"id":null,"expression":false,"generator":false,"async":false,"params":[{"type":"Identifier","start":4202,"end":4203,"name":"t"}],"body":{"type":"BlockStatement","start":4205,"end":4441,"body":[{"type":"ExpressionStatement","start":4223,"end":4427,"expression":{"type":"SequenceExpression","start":4223,"end":4426,"expressions":[{"type":"CallExpression","start":4223,"end":4242,"callee":{"type":"MemberExpression","start":4223,"end":4234,"object":{"type":"Identifier","start":4223,"end":4230,"name":"console"},"property":{"type":"Identifier","start":4231,"end":4234,"name":"log"},"computed":false,"optional":false},"arguments":[{"type":"MemberExpression","start":4235,"end":4241,"object":{"type":"Identifier","start":4235,"end":4236,"name":"t"},"property":{"type":"Identifier","start":4237,"end":4241,"name":"data"},"computed":false,"optional":false}],"optional":false},{"type":"ConditionalExpression","start":4244,"end":4426,"test":{"type":"BinaryExpression","start":4244,"end":4260,"left":{"type":"Literal","start":4244,"end":4245,"value":0,"raw":"0"},"operator":"==","right":{"type":"MemberExpression","start":4249,"end":4260,"object":{"type":"MemberExpression","start":4249,"end":4255,"object":{"type":"Identifier","start":4249,"end":4250,"name":"t"},"property":{"type":"Identifier","start":4251,"end":4255,"name":"data"},"computed":false,"optional":false},"property":{"type":"Identifier","start":4256,"end":4260,"name":"code"},"computed":false,"optional":false}},"consequent":{"type":"CallExpression","start":4263,"end":4280,"callee":{"type":"MemberExpression","start":4263,"end":4278,"object":{"type":"Identifier","start":4263,"end":4265,"name":"wx"},"property":{"type":"Identifier","start":4266,"end":4278,"name":"navigateBack"},"computed":false,"optional":false},"arguments":[],"optional":false},"alternate":{"type":"CallExpression","start":4283,"end":4426,"callee":{"type":"MemberExpression","start":4283,"end":4295,"object":{"type":"Identifier","start":4283,"end":4285,"name":"wx"},"property":{"type":"Identifier","start":4286,"end":4295,"name":"showToast"},"computed":false,"optional":false},"arguments":[{"type":"ObjectExpression","start":4296,"end":4425,"properties":[{"type":"Property","start":4318,"end":4335,"method":false,"shorthand":false,"computed":false,"key":{"type":"Identifier","start":4318,"end":4323,"name":"title"},"value":{"type":"MemberExpression","start":4325,"end":4335,"object":{"type":"MemberExpression","start":4325,"end":4331,"object":{"type":"Identifier","start":4325,"end":4326,"name":"t"},"property":{"type":"Identifier","start":4327,"end":4331,"name":"data"},"computed":false,"optional":false},"property":{"type":"Identifier","start":4332,"end":4335,"name":"msg"},"computed":false,"optional":false},"kind":"init"},{"type":"Property","start":4357,"end":4372,"method":false,"shorthand":false,"computed":false,"key":{"type":"Identifier","start":4357,"end":4361,"name":"icon"},"value":{"type":"Literal","start":4363,"end":4372,"value":"loading","raw":"\"loading\""},"kind":"init"},{"type":"Property","start":4394,"end":4407,"method":false,"shorthand":false,"computed":false,"key":{"type":"Identifier","start":4394,"end":4402,"name":"duration"},"value":{"type":"Literal","start":4404,"end":4407,"value":10000,"raw":"1e4"},"kind":"init"}]}],"optional":false}}]}}]}},"kind":"init"}]}],"optional":false}]}}]}},"kind":"init"},{"type":"Property","start":4465,"end":4487,"method":false,"shorthand":false,"computed":false,"key":{"type":"Identifier","start":4465,"end":4472,"name":"onReady"},"value":{"type":"FunctionExpression","start":4474,"end":4487,"id":null,"expression":false,"generator":false,"async":false,"params":[],"body":{"type":"BlockStatement","start":4485,"end":4487,"body":[]}},"kind":"init"},{"type":"Property","start":4493,"end":4604,"method":false,"shorthand":false,"computed":false,"key":{"type":"Identifier","start":4493,"end":4499,"name":"onShow"},"value":{"type":"FunctionExpression","start":4501,"end":4604,"id":null,"expression":false,"generator":false,"async":false,"params":[],"body":{"type":"BlockStatement","start":4512,"end":4604,"body":[{"type":"ExpressionStatement","start":4522,"end":4598,"expression":{"type":"CallExpression","start":4522,"end":4597,"callee":{"type":"MemberExpression","start":4522,"end":4546,"object":{"type":"Identifier","start":4522,"end":4524,"name":"wx"},"property":{"type":"Identifier","start":4525,"end":4546,"name":"setNavigationBarTitle"},"computed":false,"optional":false},"arguments":[{"type":"ObjectExpression","start":4547,"end":4596,"properties":[{"type":"Property","start":4561,"end":4586,"method":false,"shorthand":false,"computed":false,"key":{"type":"Identifier","start":4561,"end":4566,"name":"title"},"value":{"type":"MemberExpression","start":4568,"end":4586,"object":{"type":"MemberExpression","start":4568,"end":4580,"object":{"type":"Identifier","start":4568,"end":4569,"name":"t"},"property":{"type":"Identifier","start":4570,"end":4580,"name":"globalData"},"computed":false,"optional":false},"property":{"type":"Identifier","start":4581,"end":4586,"name":"title"},"computed":false,"optional":false},"kind":"init"}]}],"optional":false}}]}},"kind":"init"},{"type":"Property","start":4610,"end":4631,"method":false,"shorthand":false,"computed":false,"key":{"type":"Identifier","start":4610,"end":4616,"name":"onHide"},"value":{"type":"FunctionExpression","start":4618,"end":4631,"id":null,"expression":false,"generator":false,"async":false,"params":[],"body":{"type":"BlockStatement","start":4629,"end":4631,"body":[]}},"kind":"init"},{"type":"Property","start":4637,"end":4660,"method":false,"shorthand":false,"computed":false,"key":{"type":"Identifier","start":4637,"end":4645,"name":"onUnload"},"value":{"type":"FunctionExpression","start":4647,"end":4660,"id":null,"expression":false,"generator":false,"async":false,"params":[],"body":{"type":"BlockStatement","start":4658,"end":4660,"body":[]}},"kind":"init"},{"type":"Property","start":4666,"end":4698,"method":false,"shorthand":false,"computed":false,"key":{"type":"Identifier","start":4666,"end":4683,"name":"onPullDownRefresh"},"value":{"type":"FunctionExpression","start":4685,"end":4698,"id":null,"expression":false,"generator":false,"async":false,"params":[],"body":{"type":"BlockStatement","start":4696,"end":4698,"body":[]}},"kind":"init"},{"type":"Property","start":4704,"end":4732,"method":false,"shorthand":false,"computed":false,"key":{"type":"Identifier","start":4704,"end":4717,"name":"onReachBottom"},"value":{"type":"FunctionExpression","start":4719,"end":4732,"id":null,"expression":false,"generator":false,"async":false,"params":[],"body":{"type":"BlockStatement","start":4730,"end":4732,"body":[]}},"kind":"init"},{"type":"Property","start":4738,"end":4770,"method":false,"shorthand":false,"computed":false,"key":{"type":"Identifier","start":4738,"end":4755,"name":"onShareAppMessage"},"value":{"type":"FunctionExpression","start":4757,"end":4770,"id":null,"expression":false,"generator":false,"async":false,"params":[],"body":{"type":"BlockStatement","start":4768,"end":4770,"body":[]}},"kind":"init"}]}],"optional":false}}],"sourceType":"script"}