{"type":"Program","start":0,"end":315,"body":[{"type":"VariableDeclaration","start":10,"end":52,"declarations":[{"type":"VariableDeclarator","start":14,"end":51,"id":{"type":"Identifier","start":14,"end":18,"name":"util"},"init":{"type":"CallExpression","start":21,"end":51,"callee":{"type":"Identifier","start":21,"end":28,"name":"require"},"arguments":[{"type":"Literal","start":29,"end":50,"value":"../../utils/util.js","raw":"\"../../utils/util.js\""}],"optional":false}}],"kind":"var"},{"type":"ExpressionStatement","start":54,"end":315,"expression":{"type":"CallExpression","start":54,"end":314,"callee":{"type":"Identifier","start":54,"end":58,"name":"Page"},"arguments":[{"type":"ObjectExpression","start":59,"end":313,"properties":[{"type":"Property","start":65,"end":95,"method":false,"shorthand":false,"computed":false,"key":{"type":"Identifier","start":65,"end":69,"name":"data"},"value":{"type":"ObjectExpression","start":71,"end":95,"properties":[{"type":"Property","start":81,"end":89,"method":false,"shorthand":false,"computed":false,"key":{"type":"Identifier","start":81,"end":85,"name":"logs"},"value":{"type":"ArrayExpression","start":87,"end":89,"elements":[]},"kind":"init"}]},"kind":"init"},{"type":"Property","start":101,"end":311,"method":false,"shorthand":false,"computed":false,"key":{"type":"Identifier","start":101,"end":107,"name":"onLoad"},"value":{"type":"FunctionExpression","start":109,"end":311,"id":{"type":"Identifier","start":118,"end":124,"name":"onLoad"},"expression":false,"generator":false,"async":false,"params":[],"body":{"type":"BlockStatement","start":127,"end":311,"body":[{"type":"ExpressionStatement","start":137,"end":305,"expression":{"type":"CallExpression","start":137,"end":304,"callee":{"type":"MemberExpression","start":137,"end":149,"object":{"type":"ThisExpression","start":137,"end":141},"property":{"type":"Identifier","start":142,"end":149,"name":"setData"},"computed":false,"optional":false},"arguments":[{"type":"ObjectExpression","start":150,"end":303,"properties":[{"type":"Property","start":164,"end":293,"method":false,"shorthand":false,"computed":false,"key":{"type":"Identifier","start":164,"end":168,"name":"logs"},"value":{"type":"CallExpression","start":170,"end":293,"callee":{"type":"MemberExpression","start":170,"end":207,"object":{"type":"LogicalExpression","start":171,"end":202,"left":{"type":"CallExpression","start":171,"end":196,"callee":{"type":"MemberExpression","start":171,"end":188,"object":{"type":"Identifier","start":171,"end":173,"name":"wx"},"property":{"type":"Identifier","start":174,"end":188,"name":"getStorageSync"},"computed":false,"optional":false},"arguments":[{"type":"Literal","start":189,"end":195,"value":"logs","raw":"\"logs\""}],"optional":false},"operator":"||","right":{"type":"ArrayExpression","start":200,"end":202,"elements":[]}},"property":{"type":"Identifier","start":204,"end":207,"name":"map"},"computed":false,"optional":false},"arguments":[{"type":"FunctionExpression","start":208,"end":292,"id":null,"expression":false,"generator":false,"async":false,"params":[{"type":"Identifier","start":217,"end":220,"name":"log"}],"body":{"type":"BlockStatement","start":222,"end":292,"body":[{"type":"ReturnStatement","start":240,"end":278,"argument":{"type":"CallExpression","start":247,"end":277,"callee":{"type":"MemberExpression","start":247,"end":262,"object":{"type":"Identifier","start":247,"end":251,"name":"util"},"property":{"type":"Identifier","start":252,"end":262,"name":"formatTime"},"computed":false,"optional":false},"arguments":[{"type":"NewExpression","start":263,"end":276,"callee":{"type":"Identifier","start":267,"end":271,"name":"Date"},"arguments":[{"type":"Identifier","start":272,"end":275,"name":"log"}]}],"optional":false}}]}}],"optional":false},"kind":"init"}]}],"optional":false}}]}},"kind":"init"}]}],"optional":false}}],"sourceType":"script"}